MANIFEST.in
README.md
setup.py
qgiscommons.egg-info/PKG-INFO
qgiscommons.egg-info/SOURCES.txt
qgiscommons.egg-info/dependency_links.txt
qgiscommons.egg-info/top_level.txt
qgiscommons2/__init__.py
qgiscommons2/files.py
qgiscommons2/layers.py
qgiscommons2/settings.py
qgiscommons2/utils.py
qgiscommons2/gui/__init__.py
qgiscommons2/gui/authconfigselect.py
qgiscommons2/gui/checkcombobox.py
qgiscommons2/gui/iconlineedit.py
qgiscommons2/gui/paramdialog.py
qgiscommons2/gui/passwordlineedit.py
qgiscommons2/gui/settings.py
qgiscommons2/icons/eye-slash.svg
qgiscommons2/icons/eye.svg
qgiscommons2/icons/lock.svg
qgiscommons2/network/__init__.py
qgiscommons2/network/networkaccessmanager.py
qgiscommons2/network/oauth2.py