Metadata-Version: 1.0
Name: qgiscommons
Version: 2.0.11
Summary: Common functions and classes to be used in QGIS plugins
Home-page: https://github.com/boundlessgeo/lib-qgis-commons
Author: Victor Olaya
Author-email: volaya@boundlessgeo.com
License: GPL
Keywords: qgis
Platform: UNKNOWN
